reachy/__init__.py
reachy/_version.py
reachy/error.py
reachy/orbita_head_hardware_zero.npy
reachy/reachy.py
reachy/io/__init__.py
reachy/io/cam.py
reachy/io/io.py
reachy/io/luos.py
reachy/io/ws.py
reachy/parts/__init__.py
reachy/parts/arm.py
reachy/parts/hand.py
reachy/parts/head.py
reachy/parts/kinematic.py
reachy/parts/motor.py
reachy/parts/part.py
reachy/trajectory/__init__.py
reachy/trajectory/interpolation.py
reachy/trajectory/mixer.py
reachy/trajectory/player.py
reachy/trajectory/recorder.py
reachy/utils/__init__.py
reachy/utils/discovery.py
reachy/utils/dxl_config.py
reachy/utils/orbita_config.py
reachy/utils/orbita_zero.py
reachy/utils/setup_angle_limits.py
reachy-1.3.2.dist-info/LICENSE
reachy-1.3.2.dist-info/METADATA
reachy-1.3.2.dist-info/WHEEL
reachy-1.3.2.dist-info/entry_points.txt
reachy-1.3.2.dist-info/top_level.txt
reachy-1.3.2.dist-info/RECORD
