Metadata-Version: 2.1
Name: reachy
Version: 1.3.2
Summary: Open source interactive robot to explore real-world applications!
Home-page: https://github.com/pollen-robotics/reachy
Author: Pollen Robotics
Author-email: contact@pollen-robotics.com
License: UNKNOWN
Platform: UNKNOWN
Requires-Dist: pyluos (==1.2.4)
Requires-Dist: numpy
Requires-Dist: scipy (>=1.4.0)
Requires-Dist: orbita (>=0.3.1)
Requires-Dist: pyquaternion
Requires-Dist: websockets
Requires-Dist: Pillow
Provides-Extra: doc
Requires-Dist: sphinx ; extra == 'doc'
Requires-Dist: sphinx-autoapi ; extra == 'doc'
Provides-Extra: head
Requires-Dist: opencv-python ; extra == 'head'
Provides-Extra: lint
Requires-Dist: flake8 ; extra == 'lint'
Requires-Dist: pydocstyle ; extra == 'lint'
Provides-Extra: log
Requires-Dist: zzlog ; extra == 'log'
Provides-Extra: test
Requires-Dist: pytest ; extra == 'test'
